the_api/__init__.py
the_api-0.1.0.dist-info/METADATA
the_api-0.1.0.dist-info/WHEEL
the_api-0.1.0.dist-info/entry_points.txt
the_api-0.1.0.dist-info/licenses/LICENSE.txt
the_api-0.1.0.dist-info/RECORD
