Metadata-Version: 2.3
Name: the-api
Version: 0.1.0
Summary: Base for a full-featured API built with FastAPI.
Project-URL: Pull Requests, https://github.com/seapagan/the-api/pulls
Project-URL: Bug Tracker, https://github.com/seapagan/the-api/issues
Project-URL: Changelog, https://github.com/seapagan/the-api/blob/main/CHANGELOG.md
Project-URL: Repository, https://github.com/seapagan/the-api
Author-email: Grant Ramsay <grant@gnramsay.com>
License-Expression: MIT
License-File: LICENSE.txt
Classifier: Development Status :: 1 - Planning
Classifier: Framework :: FastAPI
Classifier: Intended Audience :: Developers
Classifier: License :: OSI Approved :: MIT License
Classifier: Operating System :: OS Independent
Classifier: Programming Language :: Python :: 3
Classifier: Programming Language :: Python :: 3.9
Classifier: Programming Language :: Python :: 3.10
Classifier: Programming Language :: Python :: 3.11
Classifier: Programming Language :: Python :: 3.12
Classifier: Topic :: Internet
Classifier: Topic :: Internet :: WWW/HTTP
Classifier: Topic :: Internet :: WWW/HTTP :: HTTP Servers
Classifier: Topic :: Software Development
Classifier: Topic :: Software Development :: Libraries
Classifier: Topic :: Software Development :: Libraries :: Application Frameworks
Classifier: Topic :: Software Development :: Libraries :: Python Modules
Classifier: Typing :: Typed
Requires-Python: >=3.9
Requires-Dist: fastapi[standard]>=0.115.0
